djankiserv/__init__.py
djankiserv/api/urls.py
djankiserv/api/views.py
djankiserv/apps.py
djankiserv/assets/jsonfiles/__init__.py
djankiserv/assets/jsonfiles/default_collection_conf.json
djankiserv/assets/jsonfiles/default_deck.json
djankiserv/assets/jsonfiles/default_deck_conf.json
djankiserv/assets/jsonfiles/default_model.json
djankiserv/assets/sql/sqlite3/__init__.py
djankiserv/assets/sql/sqlite3/add_indices.sql
djankiserv/assets/sql/sqlite3/create_tables.sql
djankiserv/assets/sql/sqlite3/init_col_table.sql
djankiserv/migrations/__init__.py
djankiserv/signals.py
djankiserv/sync/__init__.py
djankiserv/sync/urls.py
djankiserv/sync/views.py
djankiserv/unki/__init__.py
djankiserv/unki/cards.py
djankiserv/unki/collection.py
djankiserv/unki/database.py
djankiserv/unki/decks.py
djankiserv/unki/download.py
djankiserv/unki/models.py
djankiserv/unki/notes.py
djankiserv/unki/sched.py
djankiserv/urls.py
djankiserv-0.0.9.dist-info/LICENSE
djankiserv-0.0.9.dist-info/WHEEL
djankiserv-0.0.9.dist-info/METADATA
djankiserv-0.0.9.dist-info/RECORD
