Metadata-Version: 2.1
Name: djankiserv
Version: 0.0.9
Summary: Django-based synchronisation and API server for Anki
Home-page: https://github.com/ankicommunity/djankiserv
License: AGPL-3.0-or-later
Author: Anton Melser
Author-email: anton@melser.org
Maintainer: Anton Melser
Maintainer-email: anton@melser.org
Requires-Python: >=3.8,<4
Classifier: License :: OSI Approved :: GNU Affero General Public License v3 or later (AGPLv3+)
Classifier: Programming Language :: Python :: 3
Classifier: Programming Language :: Python :: 3.8
Classifier: Programming Language :: Python :: 3.9
Provides-Extra: mysql
Provides-Extra: pgsql
Requires-Dist: django (>=3.1,<4.0)
Requires-Dist: django-k8s (>=0.2.9,<0.3.0)
Requires-Dist: djangorestframework (>=3.11.1,<4.0.0)
Requires-Dist: djangorestframework-simplejwt (>=4.4.0,<5.0.0)
Requires-Dist: gunicorn (>=20.0.4,<21.0.0)
Requires-Dist: mysqlclient (>=2.0.1,<3.0.0); extra == "mysql"
Requires-Dist: psycopg2-binary (>=2.8.6,<3.0.0); extra == "pgsql"
Project-URL: Repository, https://github.com/ankicommunity/djankiserv
